odoo/addons/purchase_analytic/README.rst
odoo/addons/purchase_analytic/__init__.py
odoo/addons/purchase_analytic/__manifest__.py
odoo/addons/purchase_analytic/i18n/ar.po
odoo/addons/purchase_analytic/i18n/fr.po
odoo/addons/purchase_analytic/i18n/it.po
odoo/addons/purchase_analytic/i18n/pt.po
odoo/addons/purchase_analytic/i18n/purchase_analytic.pot
odoo/addons/purchase_analytic/i18n/sk.po
odoo/addons/purchase_analytic/i18n/sl.po
odoo/addons/purchase_analytic/models/__init__.py
odoo/addons/purchase_analytic/models/purchase.py
odoo/addons/purchase_analytic/readme/CONTRIBUTORS.rst
odoo/addons/purchase_analytic/readme/DESCRIPTION.rst
odoo/addons/purchase_analytic/static/description/icon.png
odoo/addons/purchase_analytic/static/description/index.html
odoo/addons/purchase_analytic/tests/__init__.py
odoo/addons/purchase_analytic/tests/test_purchase_analytic.py
odoo/addons/purchase_analytic/views/purchase_views.xml
odoo12_addon_purchase_analytic-12.0.1.0.0.99.dev15.dist-info/METADATA
odoo12_addon_purchase_analytic-12.0.1.0.0.99.dev15.dist-info/WHEEL
odoo12_addon_purchase_analytic-12.0.1.0.0.99.dev15.dist-info/top_level.txt
odoo12_addon_purchase_analytic-12.0.1.0.0.99.dev15.dist-info/RECORD
